{
  "features": [
    {
      "type": "Feature",
      "properties": {
        "name": "Лазовский заповедник имени Л. Г. Капланова",
        "description": "<p><span>Лазовский заповедник расположен на юго-востоке Приморского края. В административном отношении он находится в пределах Лазовского района. К началу заселения русскими в начале ХХ века эти места относились к числу наиболее заселённых в крае.</span></p><p><span>С 1928 года здесь существовал Южно-Уссурийский (Судзухинский) заказник площадью около 70 тыс. га. Его охраняли два конных объездчика и шесть сторожей из охотобщества. Лазовский (Судзухинский) заповедник был организован в 1935 году как филиал Сихотэ-Алинского заповедника. С 1940 он объявлен самостоятельным заповедником площадью около 150 тыс. га. Целью организации заповедника являлось сохранение и изучение природных комплексов лиановых хвойно-широколиственных и широколиственных лесов Южного Сихотэ-Алиня, охрана и восстановление популяций обитающих в них ценных и редких животных: горала, пятнистого оленя, амурского тигра.</span></p><p><span>В 1951 году заповедник был закрыт, а для сохранения ценных видов животных был организован заказник сроком на 10 лет. Заповедник был воссоздан в 1957 году на площади 172,5 тыс. га. С 1970 года заповедник, ранее именующийся Судзухинским, стал носить название — Лазовский заповедник имени Л. Г. Капланова. В 2014 году объединён с национальным парком &quot;Зов тигра&quot; в форме ФГБУ «Объединенная дирекция Лазовского государственного заповедника имени Л.Г. Капланова и национального парка «Зов тигра».</span></p>",
        "photos": [
          {
            "title": "бухта Заря",
            "link": "IMG_6946.jpg"
          },
          {
            "title": "остров Петрова и остров Бельцова",
            "link": "IMG_6242.jpg"
          },
          {
            "title": "озеро Заря",
            "link": "DJI_0017.jpg"
          },
          {
            "title": "лежбище тюленей",
            "link": "DJI_0128.jpg"
          },
          {
            "title": "домики для туристов на острове Петрова",
            "link": "Houses_Petrov.jpg"
          },
          {
            "title": "карта заповедника",
            "link": "map.jpg"
          }
        ]
      },
      "geometry": {
        "coordinates": [
          133.941842,
          43.139968
        ],
        "type": "Point"
      },
      "id": "30c8cca387638f025c256346c03c2be3"
    },
    {
      "type": "Feature",
      "properties": {
        "name": "Национальный парк \"Зов тигра\"",
        "description": "<p><span>У национального парка, несмотря на очень юный возраст, имеется большая история. Она насчитывает уже около 20 лет — со времени, когда учеными Дальневосточного научного центра Академии наук разрабатывалась &quot;Долговременная программа охраны природы и рационального использования природных ресурсов Приморского края&quot;. Именно в этой программе впервые Ю.И.Берсеневым и И.Б.Вышиным была обоснована актуальность создания на этой территории национального парка. Подробнее о ней можно узнать </span><a href='http://lazovzap.ru/about/istoriya-2/istoriya-natsionalnogo-parka-zov-tigra/'><span>здесь</span></a><span>.</span></p>"
      },
      "geometry": {
        "coordinates": [
          134.235775,
          43.547025
        ],
        "type": "Point"
      },
      "id": "4aa4314fb3915df706e06fe9f83a5aca"
    }
  ],
  "type": "FeatureCollection"
}